<?xml version="1.0" encoding="UTF-8"?>
<Defs>

    <!-- HOTL_SDBD_AbilityTheorize -->
    <JobDef>
        <defName>HOTL_TakeSecondPawnToTheorize</defName>
        <driverClass>HealersOfTheLighthouse.JobDriver_GetSecondPawnAndTheorize</driverClass>
        <reportString>discussing with TargetA.</reportString>
        <allowOpportunisticPrefix>true</allowOpportunisticPrefix>
    </JobDef>

    <JobDef>
        <defName>HOTL_FollowFirstPawnToTheorize</defName>
        <driverClass>HealersOfTheLighthouse.JobDriver_FollowFirstPawnAndTheorize</driverClass>
        <reportString>discussing with TargetA.</reportString>
        <allowOpportunisticPrefix>true</allowOpportunisticPrefix>
    </JobDef>

</Defs>